sysush_calc/__init__.py
sysush_calc/calc.py
sysush_calc-0.0.2.dist-info/LICENSE
sysush_calc-0.0.2.dist-info/METADATA
sysush_calc-0.0.2.dist-info/WHEEL
sysush_calc-0.0.2.dist-info/top_level.txt
sysush_calc-0.0.2.dist-info/RECORD
